sshkeyboard/__init__.py
sshkeyboard/_asyncio_run_backport_36.py
sshkeyboard-2.3.0.dist-info/LICENSE
sshkeyboard-2.3.0.dist-info/WHEEL
sshkeyboard-2.3.0.dist-info/METADATA
sshkeyboard-2.3.0.dist-info/RECORD
