Metadata-Version: 2.1
Name: sshkeyboard
Version: 2.3.0
Summary: sshkeyboard
Keywords: keyboard,listener,ssh,callback,headless,wsl,wsl2,server,x server,uinput,Raspberry Pi,pynput
Author: Olli Paloviita
Requires-Python: >=3.6
Classifier: Intended Audience :: Developers
Classifier: License :: OSI Approved :: MIT License
Classifier: Programming Language :: Python :: 3
Classifier: Topic :: Software Development :: Libraries :: Python Modules
Project-URL: Home, https://github.com/ollipal/sshkeyboard
